crudpack/__init__.py
crudpack/apps.py
crudpack/base.py
crudpack/decorators.py
crudpack/enums.py
crudpack/forms.py
crudpack/mixins.py
crudpack/shortcuts.py
crudpack/utils.py
crudpack/services/__init__.py
crudpack/services/fields.py
crudpack/services/packs.py
crudpack/views/__init__.py
crudpack/views/base.py
crudpack/views/create.py
crudpack/views/delete.py
crudpack/views/detail.py
crudpack/views/list.py
crudpack/views/update.py
django_crudpack-0.0.1.dist-info/METADATA
django_crudpack-0.0.1.dist-info/WHEEL
django_crudpack-0.0.1.dist-info/top_level.txt
django_crudpack-0.0.1.dist-info/RECORD
