Metadata-Version: 2.1
Name: django-crudpack
Version: 0.0.1
Summary: Utility for simplify django cruds
Author-email: Denis Siavichay <dbsiavichay@gmail.com>
Project-URL: Homepage, https://github.com/dbsiavichay/django-crudpack
Project-URL: Issues, https://github.com/dbsiavichay/django-crudpack/issues
Classifier: Programming Language :: Python :: 3
Classifier: License :: OSI Approved :: MIT License
Classifier: Operating System :: OS Independent
Requires-Python: >=3.8
